plover_delta_de/__init__.py
plover_delta_de/dictionary.py
plover_delta_de/system.py
plover_delta_de-0.3.4.dist-info/METADATA
plover_delta_de-0.3.4.dist-info/WHEEL
plover_delta_de-0.3.4.dist-info/entry_points.txt
plover_delta_de-0.3.4.dist-info/top_level.txt
plover_delta_de-0.3.4.dist-info/zip-safe
plover_delta_de-0.3.4.dist-info/RECORD
