Metadata-Version: 2.1
Name: plover-delta-de
Version: 0.3.4
Summary: German (Delta) Layout for Plover
Author: delta, Kaoffie
Keywords: plover plover_plugin
Classifier: Development Status :: 4 - Beta
Classifier: Environment :: Plugins
Classifier: Intended Audience :: End Users/Desktop
Classifier: Operating System :: OS Independent
Classifier: Programming Language :: Python :: 3
Classifier: Programming Language :: Python :: 3.6
Requires-Dist: plover (>=4.0.0.dev10)
